Outliers/Outliers.py
Outliers/__init__.py
Outliers_arjav_101703097-0.2.dist-info/METADATA
Outliers_arjav_101703097-0.2.dist-info/WHEEL
Outliers_arjav_101703097-0.2.dist-info/top_level.txt
Outliers_arjav_101703097-0.2.dist-info/RECORD
