Metadata-Version: 2.1
Name: Outliers-arjav-101703097
Version: 0.2
Summary: library to delete outliers using z-index
Home-page: https://github.com/arjavjain59998
Author: Arjav Jain
Author-email: arjavjain59998@gmail.com
License: MIT
Download-URL: https://github.com/arjavjain59998/Outliers.git
Keywords: Outliers
Platform: UNKNOWN
Classifier: Development Status :: 5 - Production/Stable
Classifier: Intended Audience :: Developers
Classifier: Topic :: Software Development :: Build Tools
Classifier: License :: OSI Approved :: MIT License
Classifier: Programming Language :: Python :: 3
Classifier: Programming Language :: Python :: 3.4
Classifier: Programming Language :: Python :: 3.5
Classifier: Programming Language :: Python :: 3.6
Classifier: Programming Language :: Python :: 3.7
Requires-Dist: python
Requires-Dist: numpy
